sphinx_typlog_theme/__init__.py
sphinx_typlog_theme/footer.html
sphinx_typlog_theme/github.html
sphinx_typlog_theme/globaltoc.html
sphinx_typlog_theme/layout.html
sphinx_typlog_theme/logo.html
sphinx_typlog_theme/page.html
sphinx_typlog_theme/relations.html
sphinx_typlog_theme/scripts.html
sphinx_typlog_theme/searchbox.html
sphinx_typlog_theme/sponsors.html
sphinx_typlog_theme/style.html
sphinx_typlog_theme/theme.conf
sphinx_typlog_theme/js/app.js
sphinx_typlog_theme/js/ga.js
sphinx_typlog_theme/static/theme.css_t
sphinx_typlog_theme/static/typlog.css
sphinx_typlog_theme-0.8.0.dist-info/LICENSE
sphinx_typlog_theme-0.8.0.dist-info/METADATA
sphinx_typlog_theme-0.8.0.dist-info/WHEEL
sphinx_typlog_theme-0.8.0.dist-info/entry_points.txt
sphinx_typlog_theme-0.8.0.dist-info/top_level.txt
sphinx_typlog_theme-0.8.0.dist-info/RECORD
