Metadata-Version: 2.1
Name: sphinx-typlog-theme
Version: 0.8.0
Summary: A typlog Sphinx theme
Home-page: https://github.com/typlog/sphinx-typlog-theme
Author: Hsiaoming Yang
Author-email: me@lepture.com
License: UNKNOWN
Platform: UNKNOWN
Classifier: Development Status :: 4 - Beta
Classifier: Intended Audience :: Developers
Classifier: License :: OSI Approved :: BSD License
Classifier: Operating System :: OS Independent
Classifier: Framework :: Sphinx
Classifier: Framework :: Sphinx :: Theme
Classifier: Programming Language :: Python
Classifier: Programming Language :: Python :: 2
Classifier: Programming Language :: Python :: 2.7
Classifier: Programming Language :: Python :: 3
Classifier: Programming Language :: Python :: 3.5
Classifier: Programming Language :: Python :: 3.6
Classifier: Programming Language :: Python :: 3.7
Classifier: Programming Language :: Python :: Implementation :: CPython
Classifier: Programming Language :: Python :: Implementation :: PyPy
Classifier: Topic :: Documentation
Classifier: Topic :: Software Development :: Documentation
Provides-Extra: dev
Requires-Dist: sphinx ; extra == 'dev'
Requires-Dist: livereload ; extra == 'dev'
